{
  "symbol": "BTCUSDT",
  "equity_curve": [
    {"event_time": "2024-01-01T12:00:00.000Z", "equity": "10000.00"},
    {"event_time": "2024-01-01T13:00:00.000Z", "equity": "10090.00"},
    {"event_time": "2024-01-02T12:00:00.000Z", "equity": "10080.00"},
    {"event_time": "2024-01-03T12:00:00.000Z", "equity": "10120.00"},
    {"event_time": "2024-01-04T12:00:00.000Z", "equity": "10030.00"},
    {"event_time": "2024-01-05T12:00:00.000Z", "equity": "10150.00"},
    {"event_time": "2024-01-06T12:00:00.000Z", "equity": "10200.00"},
    {"event_time": "2024-01-07T12:00:00.000Z", "equity": "10180.00"},
    {"event_time": "2024-01-08T12:00:00.000Z", "equity": "10300.00"},
    {"event_time": "2024-01-09T12:00:00.000Z", "equity": "10330.00"}
  ]
}
